Brinson/Brinson.py
Brinson/__init__.py
Brinson_api-1.0.1.dist-info/METADATA
Brinson_api-1.0.1.dist-info/WHEEL
Brinson_api-1.0.1.dist-info/top_level.txt
Brinson_api-1.0.1.dist-info/RECORD
