Metadata-Version: 2.1
Name: Brinson-api
Version: 1.0.1
Summary: Brinson module
Home-page: UNKNOWN
Author: lsd
Author-email: 
License: UNKNOWN
Platform: UNKNOWN
Requires-Dist: mock (==4.0.3)
Requires-Dist: numexpr (==2.6.8)
Requires-Dist: numpy (==1.19.5)
Requires-Dist: pandas (==1.0.5)
Requires-Dist: python-dateutil (==2.8.1)
Requires-Dist: pytz (==2021.1)
Requires-Dist: six (==1.15.0)
Requires-Dist: tables (==3.6.1)
